{
    "version": "1.1.2",
    "architecture": {
        "32bit": {
            "url": "https://github.com/mrfoh/httpprobe/releases/download/v1.1.2/httpprobe-v1.1.2_windows_386.tar.gz",
            "bin": [
                "httpprobe.exe"
            ],
            "hash": "6f945149b89f3bd1e02adbe7e1b3e67a9bf2a83ed038fee1fcbd2d032424f5c2"
        },
        "64bit": {
            "url": "https://github.com/mrfoh/httpprobe/releases/download/v1.1.2/httpprobe-v1.1.2_windows_amd64.tar.gz",
            "bin": [
                "httpprobe.exe"
            ],
            "hash": "a2c898dcc27bd37889f65b296cafbb864e5a0a098597c9c97f690969b3417052"
        },
        "arm64": {
            "url": "https://github.com/mrfoh/httpprobe/releases/download/v1.1.2/httpprobe-v1.1.2_windows_arm64.tar.gz",
            "bin": [
                "httpprobe.exe"
            ],
            "hash": "6772aa7b94ccc6306b7eb6966f8e9da36f21d52fc11a2c37b6304a924d5888a9"
        }
    },
    "homepage": "https://github.com/mrfoh/httpprobe",
    "license": "MIT",
    "description": "A powerful HTTP API testing tool for defining, running, and validating API tests using YAML or JSON"
}